ndgrid-0.1.5.1.dist-info/METADATA
ndgrid-0.1.5.1.dist-info/WHEEL
ndgrid-0.1.5.1.dist-info/licenses/LICENSE
ndgrid.libs/libopenblas-1dedc9fe.so.0
ndgrid.libs/libgfortran-df5d6f8d.so.5
ndgrid.libs/liblapack-426b4bf5.so.3
ndgrid.libs/libquadmath-1c3f8ec4.so.0
ndgrid/ownership.py
ndgrid/grid.py
ndgrid/__init__.py
ndgrid/shapes.py
ndgrid/_ndgridrs/__init__.py
ndgrid/_ndgridrs/ffi.py
ndgrid/_ndgridrs/_ndgridrs.so
ndgrid-0.1.5.1.dist-info/RECORD
