Metadata-Version: 2.3
Name: ndgrid
Version: 0.1.5.1
Classifier: Programming Language :: Rust
Classifier: Programming Language :: Python :: Implementation :: CPython
Requires-Dist: maturin >=1.7.2
Requires-Dist: numpy
Requires-Dist: cffi
Requires-Dist: patchelf ; platform_system == 'Linux'
Requires-Dist: ndelement
License-File: LICENSE
Summary: n-dimensional grid library.
Keywords: numerics
Home-Page: https://github.com/bempp/ndgrid
Author: Timo Betcke <timo.betcke@gmail.com>, Srinath Kailasa <srinathkailasa@gmail.com>, Matthew Scroggs <rust@mscroggs.co.uk>
Author-email: Matthew Scroggs <rust@mscroggs.co.uk>
License: BSD-3-Clause
Requires-Python: >=3.8
Project-URL: homepage, https://github.com/bempp/ndgrid
Project-URL: repository, https://github.com/bempp/ndgrid
